<annotations><filename>Shrek (282).JPEG</filename><folder>images</folder><size><width>1330</width><height>748</height><depth>3</depth></size><object><name>Shrek</name><pose>Unspecified</pose><truncated>0</truncated><difficult>0</difficult><bndbox><xmin>99.0</xmin><ymin>5.0</ymin><xmax>849.0</xmax><ymax>749.0</ymax></bndbox></object><object><name>Fiona</name><pose>Unspecified</pose><truncated>0</truncated><difficult>0</difficult><bndbox><xmin>749.0000000000001</xmin><ymin>63.0</ymin><xmax>1211.0000000000002</xmax><ymax>556.0</ymax></bndbox></object></annotations>